{
  "basics": {
    "name": "Kylie Lin",
    "label": "Student",
    "picture": "https://klin6.github.io/images/IMG_20180823_182034.jpg",
    "email": "link6@hawaii.edu",
    "phone": "808-956-0221",
    "website": "https://klin6.github.io",
    "summary": "I am studying in Computer Engineering at the University of Hawaii. I expect to graduate in Fall, 2019.",
    "location": {
      "address": "1722 Makiki st. Apt#105",
      "postalCode": "96822",
      "city": "Honolulu",
      "countryCode": "USA",
      "region": "Hawaii"
    },
    "profiles": [
      {
        "network": "github",
        "username": "klin6",
        "url": "http://github.com/klin6"
      },
      {
        "network": "linkedin",
        "username": "link6",
        "url": "http://linkedin.com/in/kylie-lin-14306a16a"
      }
    ]
  },
  "interests": [
    {
      "name": "Software",
      "keywords": [
        "Learned Java, C, and C++ so far, now on Javascript."
      ]
    },
    {
      "name": "Apple products",
      "keywords": [
        "All coding on Macbook Air so far."
      ]
    }
  ],
  "skills": [
    {
      "name": "Languages and Frameworks",
      "level": "",
      "keywords": [
        "C",
        "C++",
        "Java"
      ]
    },
    {
      "name": "Toolsets/OS",
      "level": "",
      "keywords": [
        "MacOS",
        "Ubuntu",
        "Git/GitHub"
      ]
    }
  ],
  "education": [
    {
      "institution": "University of Hawaii at Manoa, Honolulu, HI",
      "area": "Computer Engineer (expected Spring, 2019)",
      "studyType": "B.S.",
      "startDate": "2015-08-01",
      "endDate": "Present",
      "gpa": "3.01",
      "courses": [
        "EE160, EE205, ICS111"
      ]
    }
  ],
  "work": [
    {
      "company": "UH Engineering Department",
      "position": "Computer Lab Monitor",
      "website": "http://ee.hawaii.edu/student/index.php?stc=1&stp=105",
      "startDate": "2018-05-08",
      "endDate": "2019-04-29",
      "summary": "",
      "highlights": [
        "Monitor engineering computer lab for students"
      ]
    }
  ],
  "awards": [
    {
      "title": "Local 798 Scholarship",
      "date": "2016",
      "awarder": "Union Association",
      "summary": "Scholarships awarded to relatives of Union workers"
    }
  ],
  "references": [
    {
      "name": "Available upon request",
      "reference": ""
    }
  ]
}
